xyh_zxh/__init__.py
xyh_zxh/demo/__init__.py
xyh_zxh/demo/demo1.py
xyhzxh-0.1.dist-info/METADATA
xyhzxh-0.1.dist-info/WHEEL
xyhzxh-0.1.dist-info/top_level.txt
xyhzxh-0.1.dist-info/RECORD
