Metadata-Version: 2.1
Name: xyhzxh
Version: 0.1
Summary: a test
Author: yonghuiXu
Author-email: 2541128175@qq.com
